cythonintersectgroupercython/README.MD
cythonintersectgroupercython/__init__.py
cythonintersectgroupercython/intercg.pyx
cythonintersectgroupercython/requirements.txt
cythonintersectgroupercython/thirdparty.json
cythonintersectgroupercython-0.10.dist-info/LICENSE.rst
cythonintersectgroupercython-0.10.dist-info/METADATA
cythonintersectgroupercython-0.10.dist-info/WHEEL
cythonintersectgroupercython-0.10.dist-info/top_level.txt
cythonintersectgroupercython-0.10.dist-info/RECORD
