Metadata-Version: 2.1
Name: cythonintersectgroupercython
Version: 0.10
Summary: finds direct and nested intersections of lists
Home-page: https://github.com/hansalemaos/cythonintersectgroupercython
Author: Johannes Fischer
Author-email: aulasparticularesdealemaosp@gmail.com
License: MIT
Keywords: intersection,group
Classifier: Development Status :: 4 - Beta
Classifier: Programming Language :: Python :: 3 :: Only
Classifier: Programming Language :: Python :: 3.10
Classifier: Topic :: Software Development :: Libraries :: Python Modules
Classifier: Topic :: Utilities
License-File: LICENSE.rst
Requires-Dist: cycompi
Requires-Dist: flatten-any-dict-iterable-or-whatsoever
Requires-Dist: numpy
Requires-Dist: numpycythonpermutations
